{"expireTime":9007200875059794000,"key":"create-remote-file-node-https://dev-esfwindows.pantheonsite.io/sites/default/files/2020-01/5db08e0170af09bdb1f1ffc2_fixed-window-zola-02-thumb.jpg","val":{"connection":"close","content-length":"87782","content-type":"image/jpeg","etag":"\"6037f718-156e6\"","expires":"Thu, 06 May 2021 16:33:22 GMT","last-modified":"Thu, 25 Feb 2021 19:14:32 GMT","server":"nginx","strict-transport-security":"max-age=300","x-pantheon-styx-hostname":"styx-fe4-a-68dbfbc774-gmg2b","x-styx-req-id":"c63177da-ae88-11eb-b12d-22e18ff8b3f5","cache-control":"no-cache, must-revalidate","date":"Thu, 06 May 2021 16:33:23 GMT","x-served-by":"cache-mdw17379-MDW, cache-wdc5530-WDC","x-cache":"MISS, MISS","x-cache-hits":"0, 0","x-timer":"S1620318803.870490,VS0,VE371","x-robots-tag":"noindex","age":"0","accept-ranges":"bytes","via":"1.1 varnish, 1.1 varnish"}}