{"expireTime":9007200871268325000,"key":"create-remote-file-node-https://dev-esfwindows.pantheonsite.io/sites/default/files/2020-02/ASE_60_80_m_Villa.jpg","val":{"connection":"close","content-length":"198127","content-type":"image/jpeg","etag":"\"6037f71f-305ef\"","expires":"Tue, 23 Mar 2021 19:22:11 GMT","last-modified":"Thu, 25 Feb 2021 19:14:39 GMT","server":"nginx","strict-transport-security":"max-age=300","x-pantheon-styx-hostname":"styx-fe4-a-68dbfbc774-bj54l","x-styx-req-id":"11cb1215-8c0d-11eb-9c22-86113990e5d8","cache-control":"no-cache, must-revalidate","date":"Tue, 23 Mar 2021 19:22:12 GMT","x-served-by":"cache-mdw17326-MDW, cache-wdc5542-WDC","x-cache":"MISS, MISS","x-cache-hits":"0, 0","x-timer":"S1616527333.575278,VS0,VE57","x-robots-tag":"noindex","age":"0","accept-ranges":"bytes","via":"1.1 varnish, 1.1 varnish"}}