{"expireTime":9007200870667050000,"key":"create-remote-file-node-https://dev-esfwindows.pantheonsite.io/sites/default/files/2020-02/pvc-u_home.jpg","val":{"connection":"close","content-length":"45822","content-type":"image/jpeg","etag":"\"6037f728-b2fe\"","expires":"Tue, 16 Mar 2021 20:20:57 GMT","last-modified":"Thu, 25 Feb 2021 19:14:48 GMT","server":"nginx","strict-transport-security":"max-age=300","x-pantheon-styx-hostname":"styx-fe4-a-6b4c66d56-69l42","x-styx-req-id":"1e496efa-8695-11eb-a429-760ea95cbcfe","cache-control":"no-cache, must-revalidate","date":"Tue, 16 Mar 2021 20:20:58 GMT","x-served-by":"cache-mdw17381-MDW, cache-wdc5550-WDC","x-cache":"MISS, MISS","x-cache-hits":"0, 0","x-timer":"S1615926058.114457,VS0,VE50","x-robots-tag":"noindex","age":"0","accept-ranges":"bytes","via":"1.1 varnish, 1.1 varnish"}}