{"expireTime":9007200857451694000,"key":"create-remote-file-node-https://dev-esfwindows.pantheonsite.io/sites/default/files/2020-01/5ce87b652b1e2e463af1da42_argon-gas-fixed-window.jpg","val":{"connection":"close","content-length":"31885","content-type":"image/jpeg","etag":"\"5f74d883-7c8d\"","expires":"Wed, 14 Oct 2020 21:25:01 GMT","last-modified":"Wed, 30 Sep 2020 19:12:03 GMT","server":"nginx","strict-transport-security":"max-age=300","x-pantheon-styx-hostname":"styx-fe4-b-55f8cd4fb8-7qsv5","x-styx-req-id":"b839ab57-0e63-11eb-9ce3-968cc2f2c330","cache-control":"no-cache, must-revalidate","date":"Wed, 14 Oct 2020 21:25:02 GMT","x-served-by":"cache-mdw17346-MDW, cache-fty21352-FTY","x-cache":"MISS, MISS","x-cache-hits":"0, 0","x-timer":"S1602710702.011633,VS0,VE651","x-robots-tag":"noindex","age":"0","accept-ranges":"bytes","via":"1.1 varnish"}}