{"expireTime":9007200855450471000,"key":"create-remote-file-node-https://dev-esfwindows.pantheonsite.io/sites/default/files/2020-09/ns4729.jpg","val":{"connection":"close","content-length":"22772","content-type":"image/jpeg","etag":"\"5f68e0a7-58f4\"","expires":"Mon, 21 Sep 2020 17:31:19 GMT","last-modified":"Mon, 21 Sep 2020 17:19:35 GMT","server":"nginx","strict-transport-security":"max-age=300","x-pantheon-styx-hostname":"styx-fe4-b-548c7f4b68-wvltd","x-styx-req-id":"431b8b06-fc30-11ea-9eba-6aa66bbf6c1c","cache-control":"no-cache, must-revalidate","date":"Mon, 21 Sep 2020 17:31:20 GMT","x-served-by":"cache-mdw17347-MDW, cache-dca17773-DCA","x-cache":"MISS, MISS","x-cache-hits":"0, 0","x-timer":"S1600709480.257102,VS0,VE51","x-robots-tag":"noindex","age":"0","accept-ranges":"bytes","via":"1.1 varnish"}}