{"expireTime":9007200870551636000,"key":"create-remote-file-node-https://dev-esfwindows.pantheonsite.io/sites/default/files/2020-10/Amleto-2.jpg","val":{"connection":"close","content-length":"1013533","content-type":"image/jpeg","etag":"\"6037f7ab-f771d\"","expires":"Mon, 15 Mar 2021 12:17:20 GMT","last-modified":"Thu, 25 Feb 2021 19:16:59 GMT","server":"nginx","strict-transport-security":"max-age=300","x-pantheon-styx-hostname":"styx-fe4-b-7fbc4c4c64-sqw8v","x-styx-req-id":"64a5feaa-8588-11eb-8ef8-ca4786962727","cache-control":"no-cache, must-revalidate","date":"Mon, 15 Mar 2021 12:17:21 GMT","x-served-by":"cache-mdw17368-MDW, cache-wdc5535-WDC","x-cache":"MISS, MISS","x-cache-hits":"0, 0","x-timer":"S1615810642.541603,VS0,VE44","x-robots-tag":"noindex","age":"0","accept-ranges":"bytes","via":"1.1 varnish, 1.1 varnish"}}