{"expireTime":9007200870559556000,"key":"create-remote-file-node-https://dev-esfwindows.pantheonsite.io/sites/default/files/2020-09/ns4743-bronzograffiatoopaco.png","val":{"connection":"close","content-length":"456466","content-type":"image/png","etag":"\"6037f787-6f712\"","expires":"Mon, 15 Mar 2021 14:29:19 GMT","last-modified":"Thu, 25 Feb 2021 19:16:23 GMT","server":"nginx","strict-transport-security":"max-age=300","x-pantheon-styx-hostname":"styx-fe4-a-6b4c66d56-glzql","x-styx-req-id":"d4e3bb19-859a-11eb-ab2b-be47f1660b62","cache-control":"no-cache, must-revalidate","date":"Mon, 15 Mar 2021 14:29:20 GMT","x-served-by":"cache-mdw17376-MDW, cache-wdc5537-WDC","x-cache":"MISS, MISS","x-cache-hits":"0, 0","x-timer":"S1615818561.790580,VS0,VE103","x-robots-tag":"noindex","age":"0","accept-ranges":"bytes","via":"1.1 varnish, 1.1 varnish"}}