{"expireTime":9007200854925574000,"key":"create-remote-file-node-https://dev-esfwindows.pantheonsite.io/sites/default/files/2020-09/story.jpg","val":{"connection":"close","content-length":"21015","content-type":"image/jpeg","etag":"\"5f60dfe3-5217\"","expires":"Tue, 15 Sep 2020 15:43:01 GMT","last-modified":"Tue, 15 Sep 2020 15:38:11 GMT","server":"nginx","strict-transport-security":"max-age=300","x-pantheon-styx-hostname":"styx-fe4-a-7d74f95bf6-v86tx","x-styx-req-id":"23e1d51e-f76a-11ea-a83e-aeda1434bb81","cache-control":"no-cache, must-revalidate","date":"Tue, 15 Sep 2020 15:43:02 GMT","x-served-by":"cache-mdw17330-MDW, cache-dca17727-DCA","x-cache":"MISS, MISS","x-cache-hits":"0, 0","x-timer":"S1600184583.864651,VS0,VE65","x-robots-tag":"noindex","age":"0","accept-ranges":"bytes","via":"1.1 varnish"}}