{"expireTime":9007200873933005000,"key":"create-remote-file-node-https://dev-esfwindows.pantheonsite.io/sites/default/files/2020-02/Gemini_Integral_systemy_drewniano-aluminiowe.jpg","val":{"connection":"close","content-length":"50809","content-type":"image/jpeg","etag":"\"6037f732-c679\"","expires":"Fri, 23 Apr 2021 15:33:32 GMT","last-modified":"Thu, 25 Feb 2021 19:14:58 GMT","server":"nginx","strict-transport-security":"max-age=300","x-pantheon-styx-hostname":"styx-fe4-b-6c5dfb7cc8-wrj5v","x-styx-req-id":"4389f6d1-a449-11eb-8677-42fd8e507f15","cache-control":"no-cache, must-revalidate","date":"Fri, 23 Apr 2021 15:33:33 GMT","x-served-by":"cache-mdw17342-MDW, cache-wdc5538-WDC","x-cache":"MISS, MISS","x-cache-hits":"0, 0","x-timer":"S1619192014.745985,VS0,VE51","x-robots-tag":"noindex","age":"0","accept-ranges":"bytes","via":"1.1 varnish, 1.1 varnish"}}