{"expireTime":9007200871268319000,"key":"create-remote-file-node-https://dev-esfwindows.pantheonsite.io/sites/default/files/2020-01/5db08e0170af09bdb1f1ffc2_fixed-window-zola-02-thumb.jpg","val":{"connection":"close","content-length":"87782","content-type":"image/jpeg","etag":"\"6037f718-156e6\"","expires":"Tue, 23 Mar 2021 19:22:07 GMT","last-modified":"Thu, 25 Feb 2021 19:14:32 GMT","server":"nginx","strict-transport-security":"max-age=300","x-pantheon-styx-hostname":"styx-fe4-b-6c5dfb7cc8-7j7tg","x-styx-req-id":"0f3383bb-8c0d-11eb-aa50-8ec4c3ec3a57","cache-control":"no-cache, must-revalidate","date":"Tue, 23 Mar 2021 19:22:08 GMT","x-served-by":"cache-mdw17332-MDW, cache-wdc5520-WDC","x-cache":"MISS, MISS","x-cache-hits":"0, 0","x-timer":"S1616527328.229432,VS0,VE296","x-robots-tag":"noindex","age":"0","accept-ranges":"bytes","via":"1.1 varnish, 1.1 varnish"}}