{"expireTime":9007200867641523000,"key":"create-remote-file-node-https://dev-esfwindows.pantheonsite.io/sites/default/files/2020-10/Progetto-senza-titolo-440x340.jpg","val":{"connection":"close","content-length":"39703","content-type":"image/jpeg","etag":"\"6009abec-9b17\"","expires":"Tue, 09 Feb 2021 19:55:33 GMT","last-modified":"Thu, 21 Jan 2021 16:29:32 GMT","server":"nginx","strict-transport-security":"max-age=300","x-pantheon-styx-hostname":"styx-fe4-b-649d688684-9sq97","x-styx-req-id":"c599634d-6b10-11eb-af73-fe26c31712af","cache-control":"no-cache, must-revalidate","date":"Tue, 09 Feb 2021 19:55:34 GMT","x-served-by":"cache-mdw17368-MDW, cache-wdc5573-WDC","x-cache":"MISS, MISS","x-cache-hits":"0, 0","x-timer":"S1612900534.358228,VS0,VE106","x-robots-tag":"noindex","age":"0","accept-ranges":"bytes","via":"1.1 varnish, 1.1 varnish"}}