{"expireTime":9007200873668273000,"key":"create-remote-file-node-https://dev-esfwindows.pantheonsite.io/sites/default/files/2020-09/ns4720.jpg","val":{"connection":"close","content-length":"24130","content-type":"image/jpeg","etag":"\"6037f787-5e42\"","expires":"Tue, 20 Apr 2021 14:01:21 GMT","last-modified":"Thu, 25 Feb 2021 19:16:23 GMT","server":"nginx","strict-transport-security":"max-age=300","x-pantheon-styx-hostname":"styx-fe4-b-6c5dfb7cc8-dsr58","x-styx-req-id":"e327a759-a1e0-11eb-8bb7-16b0f439e909","cache-control":"no-cache, must-revalidate","date":"Tue, 20 Apr 2021 14:01:22 GMT","x-served-by":"cache-mdw17326-MDW, cache-wdc5544-WDC","x-cache":"MISS, MISS","x-cache-hits":"0, 0","x-timer":"S1618927282.054485,VS0,VE44","x-robots-tag":"noindex","age":"0","accept-ranges":"bytes","via":"1.1 varnish, 1.1 varnish"}}