{"expireTime":9007200864858189000,"key":"create-remote-file-node-https://dev-esfwindows.pantheonsite.io/sites/default/files/2020-09/ns4716.jpg","val":{"connection":"close","content-length":"21967","content-type":"image/jpeg","etag":"\"5fc67777-55cf\"","expires":"Fri, 08 Jan 2021 14:46:45 GMT","last-modified":"Tue, 01 Dec 2020 17:03:51 GMT","server":"nginx","strict-transport-security":"max-age=300","x-pantheon-styx-hostname":"styx-fe4-b-7985f65b8b-t5pvx","x-styx-req-id":"54fdc4d6-51c0-11eb-9dd8-a22e98d1a2c7","cache-control":"no-cache, must-revalidate","date":"Fri, 08 Jan 2021 14:46:46 GMT","x-served-by":"cache-mdw17351-MDW, cache-wdc5565-WDC","x-cache":"MISS, MISS","x-cache-hits":"0, 0","x-timer":"S1610117207.626575,VS0,VE139","x-robots-tag":"noindex","age":"0","accept-ranges":"bytes","via":"1.1 varnish, 1.1 varnish"}}