{"expireTime":9007200868841752000,"key":"create-remote-file-node-https://dev-esfwindows.pantheonsite.io/sites/default/files/2020-09/artemisia-cromo.jpg","val":{"connection":"close","content-length":"21826","content-type":"image/jpeg","etag":"\"6009abde-5542\"","expires":"Tue, 23 Feb 2021 17:19:19 GMT","last-modified":"Thu, 21 Jan 2021 16:29:18 GMT","server":"nginx","strict-transport-security":"max-age=300","x-pantheon-styx-hostname":"styx-fe4-b-649d688684-g9bm2","x-styx-req-id":"445ced55-75fb-11eb-bf59-129971926bc2","cache-control":"no-cache, must-revalidate","date":"Tue, 23 Feb 2021 17:19:20 GMT","x-served-by":"cache-mdw17325-MDW, cache-wdc5540-WDC","x-cache":"MISS, MISS","x-cache-hits":"0, 0","x-timer":"S1614100761.895758,VS0,VE43","x-robots-tag":"noindex","age":"0","accept-ranges":"bytes","via":"1.1 varnish, 1.1 varnish"}}