{"expireTime":9007200875059807000,"key":"create-remote-file-node-https://dev-esfwindows.pantheonsite.io/sites/default/files/2020-09/primula.jpg","val":{"connection":"close","content-length":"17776","content-type":"image/jpeg","etag":"\"6037f789-4570\"","expires":"Thu, 06 May 2021 16:33:35 GMT","last-modified":"Thu, 25 Feb 2021 19:16:25 GMT","server":"nginx","strict-transport-security":"max-age=300","x-pantheon-styx-hostname":"styx-fe4-a-68dbfbc774-tvn2b","x-styx-req-id":"ce82aa1e-ae88-11eb-bb5c-d283e8b80392","cache-control":"no-cache, must-revalidate","date":"Thu, 06 May 2021 16:33:36 GMT","x-served-by":"cache-mdw17346-MDW, cache-wdc5546-WDC","x-cache":"MISS, MISS","x-cache-hits":"0, 0","x-timer":"S1620318817.824194,VS0,VE57","x-robots-tag":"noindex","age":"0","accept-ranges":"bytes","via":"1.1 varnish, 1.1 varnish"}}