{"expireTime":9007200869692891000,"key":"create-remote-file-node-https://dev-esfwindows.pantheonsite.io/sites/default/files/2020-10/BladeCSA-3-660x660.jpg","val":{"connection":"close","content-length":"22692","content-type":"image/jpeg","etag":"\"6037f7ad-58a4\"","expires":"Fri, 05 Mar 2021 13:44:59 GMT","last-modified":"Thu, 25 Feb 2021 19:17:01 GMT","server":"nginx","strict-transport-security":"max-age=300","x-pantheon-styx-hostname":"styx-fe4-b-7fbc4c4c64-q8hxx","x-styx-req-id":"fad2a722-7db8-11eb-b265-9ad421402f7c","cache-control":"no-cache, must-revalidate","date":"Fri, 05 Mar 2021 13:45:00 GMT","x-served-by":"cache-mdw17379-MDW, cache-wdc5534-WDC","x-cache":"MISS, MISS","x-cache-hits":"0, 0","x-timer":"S1614951900.034181,VS0,VE45","x-robots-tag":"noindex","age":"0","accept-ranges":"bytes","via":"1.1 varnish, 1.1 varnish"}}