{"expireTime":9007200865466836000,"key":"create-remote-file-node-https://dev-esfwindows.pantheonsite.io/sites/default/files/2020-02/DSC_9912.JPG","val":{"connection":"close","content-length":"3437065","content-type":"image/jpeg","etag":"\"5fc6776f-347209\"","expires":"Fri, 15 Jan 2021 15:50:42 GMT","last-modified":"Tue, 01 Dec 2020 17:03:43 GMT","server":"nginx","strict-transport-security":"max-age=300","x-pantheon-styx-hostname":"styx-fe4-a-7766cc6998-nsk9h","x-styx-req-id":"6cc92308-5749-11eb-bf4d-9aa52e6b0cfa","cache-control":"no-cache, must-revalidate","date":"Fri, 15 Jan 2021 15:50:43 GMT","x-served-by":"cache-mdw17369-MDW, cache-wdc5537-WDC","x-cache":"MISS, MISS","x-cache-hits":"0, 0","x-timer":"S1610725843.412891,VS0,VE68","x-robots-tag":"noindex","age":"0","accept-ranges":"bytes","via":"1.1 varnish, 1.1 varnish"}}