{"expireTime":9007200855450471000,"key":"create-remote-file-node-https://dev-esfwindows.pantheonsite.io/sites/default/files/2020-09/ns4718.jpg","val":{"connection":"close","content-length":"14733","content-type":"image/jpeg","etag":"\"5f68df09-398d\"","expires":"Mon, 21 Sep 2020 17:31:19 GMT","last-modified":"Mon, 21 Sep 2020 17:12:41 GMT","server":"nginx","strict-transport-security":"max-age=300","x-pantheon-styx-hostname":"styx-fe4-a-7d74f95bf6-v86tx","x-styx-req-id":"430f51d5-fc30-11ea-8e7f-aeda1434bb81","cache-control":"no-cache, must-revalidate","date":"Mon, 21 Sep 2020 17:31:20 GMT","x-served-by":"cache-mdw17356-MDW, cache-dca17769-DCA","x-cache":"MISS, MISS","x-cache-hits":"0, 0","x-timer":"S1600709480.177842,VS0,VE47","x-robots-tag":"noindex","age":"0","accept-ranges":"bytes","via":"1.1 varnish"}}